agentic_fleet/__init__.py
agentic_fleet/main.py
agentic_fleet/py.typed
agentic_fleet/agents/__init__.py
agentic_fleet/agents/base.py
agentic_fleet/agents/coordinator.py
agentic_fleet/agents/foundry.py
agentic_fleet/agents/prompts.py
agentic_fleet/api/__init__.py
agentic_fleet/api/deps.py
agentic_fleet/api/lifespan.py
agentic_fleet/api/main.py
agentic_fleet/api/middleware.py
agentic_fleet/api/api_v1/__init__.py
agentic_fleet/api/api_v1/api.py
agentic_fleet/api/events/__init__.py
agentic_fleet/api/events/mapping.py
agentic_fleet/api/routes/__init__.py
agentic_fleet/api/routes/agents.py
agentic_fleet/api/routes/chat.py
agentic_fleet/api/routes/conversations.py
agentic_fleet/api/routes/dspy.py
agentic_fleet/api/routes/history.py
agentic_fleet/api/routes/nlu.py
agentic_fleet/api/routes/optimize.py
agentic_fleet/api/routes/sessions.py
agentic_fleet/api/routes/workflows.py
agentic_fleet/cli/__init__.py
agentic_fleet/cli/console.py
agentic_fleet/cli/display.py
agentic_fleet/cli/runner.py
agentic_fleet/cli/utils.py
agentic_fleet/cli/commands/__init__.py
agentic_fleet/cli/commands/dev.py
agentic_fleet/cli/commands/eval.py
agentic_fleet/cli/commands/handoff.py
agentic_fleet/cli/commands/inspect.py
agentic_fleet/cli/commands/optimize.py
agentic_fleet/cli/commands/run.py
agentic_fleet/config/workflow_config.yaml
agentic_fleet/core/__init__.py
agentic_fleet/core/bridge_middleware.py
agentic_fleet/core/config.py
agentic_fleet/core/conversation_store.py
agentic_fleet/core/logging.py
agentic_fleet/core/middleware.py
agentic_fleet/core/settings.py
agentic_fleet/core/storage.py
agentic_fleet/data/evaluation_tasks.jsonl
agentic_fleet/data/golden_dataset.json
agentic_fleet/data/history_evaluation_tasks.jsonl
agentic_fleet/data/supervisor_examples.json
agentic_fleet/dspy_modules/__init__.py
agentic_fleet/dspy_modules/answer_quality.py
agentic_fleet/dspy_modules/assertions.py
agentic_fleet/dspy_modules/compiled_registry.py
agentic_fleet/dspy_modules/handoff_signatures.py
agentic_fleet-0.6.95.dist-info/METADATA
agentic_fleet-0.6.95.dist-info/WHEEL
agentic_fleet-0.6.95.dist-info/entry_points.txt
agentic_fleet-0.6.95.dist-info/licenses/LICENSE
agentic_fleet-0.6.95.dist-info/RECORD
