Metadata-Version: 2.4
Name: agentic-fleet
Version: 0.6.95
Summary: Multi-agent orchestration system built with Microsoft Agent Framework's Magentic Fleet pattern
Project-URL: Homepage, https://github.com/Qredence/agentic-fleet
Project-URL: Documentation, https://github.com/Qredence/agentic-fleet/docs
Project-URL: Repository, https://github.com/Qredence/agentic-fleet
Project-URL: Issues, https://github.com/Qredence/agentic-fleet/issues
Author-email: Qredence <contact@qredence.ai>
License: MIT License
License-File: LICENSE
Keywords: agents,ai,magentic
Classifier: Development Status :: 4 - Beta
Classifier: Framework :: AsyncIO
Classifier: Intended Audience :: Developers
Classifier: License :: OSI Approved :: MIT License
Classifier: Programming Language :: Python :: 3.12
Classifier: Programming Language :: Python :: 3.13
Classifier: Topic :: Scientific/Engineering :: Artificial Intelligence
Classifier: Topic :: Software Development :: Libraries :: Python Modules
Classifier: Typing :: Typed
Requires-Python: <4,>=3.12
Requires-Dist: agent-framework-azure-ai-search==1.0.0b251211
Requires-Dist: agent-framework-azure-ai==1.0.0b251211
Requires-Dist: agent-framework-core==1.0.0b251211
Requires-Dist: agent-framework==1.0.0b251211
Requires-Dist: aiofiles<26.0,>=25.1.0
Requires-Dist: aiohttp>=3.9.0
Requires-Dist: aiomqtt>=1.0.0
Requires-Dist: aiosqlite>=0.20.0
Requires-Dist: anyio<5.0,>=4.11.0
Requires-Dist: asyncer<1.0,>=0.0.8
Requires-Dist: azure-ai-agents<1.3,>=1.2.0b5
Requires-Dist: azure-ai-evaluation<2.0,>=1.12.0
Requires-Dist: azure-ai-projects==2.0.0b2
Requires-Dist: azure-cosmos<5.0,>=4.8.0
Requires-Dist: azure-identity<2.0,>=1.25.1
Requires-Dist: azure-monitor-opentelemetry-exporter>=1.0.0b46
Requires-Dist: azure-monitor-opentelemetry>=1.8.3
Requires-Dist: azure-search-documents>=11.6.0
Requires-Dist: click>=8.1.0
Requires-Dist: databases[asyncpg]<1.0,>=0.7.0
Requires-Dist: dill>=0.3.8
Requires-Dist: dspy>=3.0.3
Requires-Dist: fastapi[standard]<1.0,>=0.120.1
Requires-Dist: gepa[dspy]<1.0,>=0.0.17
Requires-Dist: httpx>=0.24.0
Requires-Dist: ipykernel<8.0,>=7.0.1
Requires-Dist: matplotlib>=3.6.0
Requires-Dist: mcp>=1.21.0
Requires-Dist: mlflow>=3.6.0
Requires-Dist: numpy>=1.24.0
Requires-Dist: openai>=2.5.1
Requires-Dist: opentelemetry-exporter-otlp-proto-http>=1.38.0
Requires-Dist: pandas>=1.5.0
Requires-Dist: playwright>=1.40.0
Requires-Dist: plotly>=5.10.0
Requires-Dist: prometheus-client>=0.16.0
Requires-Dist: prometheus-fastapi-instrumentator>=6.1.0
Requires-Dist: prompt-toolkit<4.0,>=3.0.47
Requires-Dist: psutil>=5.9.0
Requires-Dist: pydantic-settings<3.0,>=2.3.2
Requires-Dist: pydantic<3.0,>=2.12.3
Requires-Dist: python-dotenv<2.0,>=1.2.1
Requires-Dist: python-json-logger>=2.0.7
Requires-Dist: pytz>=2024.1
Requires-Dist: pyyaml<7.0,>=6.0.3
Requires-Dist: requests>=2.28.0
Requires-Dist: rich>=14.2.0
Requires-Dist: scipy>=1.9.0
Requires-Dist: seaborn>=0.11.0
Requires-Dist: setuptools>=80.9.0
Requires-Dist: sqlalchemy>=2.0.44
Requires-Dist: statsd>=3.3.0
Requires-Dist: tavily-python>=0.7.12
Requires-Dist: tenacity>=8.2.3
Requires-Dist: textual>=6.5.0
Requires-Dist: tiktoken<1.0,>=0.12.0
Requires-Dist: typer<0.21.0,>=0.20.0
Requires-Dist: uvicorn[standard]>=0.24.0
Requires-Dist: websockets>=10.4
Provides-Extra: a2a
Requires-Dist: agent-framework-a2a==1.0.0b251211; extra == 'a2a'
Provides-Extra: all
Requires-Dist: agent-framework-devui==1.0.0b251211; extra == 'all'
Requires-Dist: azure-ai-agents==1.2.0b5; extra == 'all'
Requires-Dist: azure-ai-evaluation<2.0,>=1.12.0; extra == 'all'
Requires-Dist: azure-ai-projects==2.0.0b2; extra == 'all'
Requires-Dist: azure-identity<2.0,>=1.25.1; extra == 'all'
Requires-Dist: azure-monitor-opentelemetry>=1.6.0; extra == 'all'
Requires-Dist: prompt-toolkit<4.0,>=3.0.47; extra == 'all'
Requires-Dist: rich>=14.2.0; extra == 'all'
Provides-Extra: azure
Requires-Dist: azure-ai-agents==1.2.0b5; extra == 'azure'
Requires-Dist: azure-ai-projects==2.0.0b2; extra == 'azure'
Requires-Dist: azure-identity<2.0,>=1.25.1; extra == 'azure'
Provides-Extra: azurefunctions
Requires-Dist: agent-framework-azurefunctions==1.0.0b251211; extra == 'azurefunctions'
Provides-Extra: declarative
Requires-Dist: agent-framework-declarative==1.0.0b251211; extra == 'declarative'
Provides-Extra: evaluation
Requires-Dist: azure-ai-evaluation<2.0,>=1.12.0; extra == 'evaluation'
Provides-Extra: tracing
Requires-Dist: azure-monitor-opentelemetry>=1.6.0; extra == 'tracing'
Provides-Extra: ui
Requires-Dist: agent-framework-devui==1.0.0b251211; extra == 'ui'
Requires-Dist: prompt-toolkit<4.0,>=3.0.47; extra == 'ui'
Requires-Dist: rich>=14.2.0; extra == 'ui'
